NCapybaraLib/All.py
NCapybaraLib/Containers.py
NCapybaraLib/DoomWAD.py
NCapybaraLib/Math.py
NCapybaraLib/ROT.py
NCapybaraLib/String.py
NCapybaraLib/__init__.py
NCapybaraLib/_internal/Containers.py
NCapybaraLib/_internal/DoomWAD.py
NCapybaraLib/_internal/Math.py
NCapybaraLib/_internal/ROT.py
NCapybaraLib/_internal/String.py
NCapybaraLib/_internal/init.py
ncapybaralib-1.3.0.dist-info/licenses/LICENSE.md
ncapybaralib-1.3.0.dist-info/METADATA
ncapybaralib-1.3.0.dist-info/WHEEL
ncapybaralib-1.3.0.dist-info/top_level.txt
ncapybaralib-1.3.0.dist-info/RECORD
