Metadata-Version: 2.4
Name: NCapybaraLib
Version: 1.3.0
Summary: A small library with a bunch of functions and thingies I made for fun.
Author: NorbCodes
Maintainer: NorbCodes
License-Expression: MIT
Project-URL: Github Repo, https://github.com/norbcodes/NCapybaraLib
Project-URL: Bug Tracker, https://github.com/norbcodes/NCapybaraLib/issues
Project-URL: Pull Requests, https://github.com/norbcodes/NCapybaraLib/pulls
Keywords: capybara,math,functions,library
Classifier: Programming Language :: Python :: 3
Classifier: Programming Language :: Python :: 3.11
Classifier: Programming Language :: Python :: 3.12
Classifier: Natural Language :: English
Classifier: Operating System :: Microsoft :: Windows :: Windows 10
Classifier: Operating System :: OS Independent
Classifier: Development Status :: 5 - Production/Stable
Requires-Python: >=3.11
License-File: LICENSE.md
Dynamic: license-file
